paddlennunet/__init__.py
paddle_nnUNet-0.0.2.dist-info/LICENSE
paddle_nnUNet-0.0.2.dist-info/METADATA
paddle_nnUNet-0.0.2.dist-info/WHEEL
paddle_nnUNet-0.0.2.dist-info/top_level.txt
paddle_nnUNet-0.0.2.dist-info/RECORD
