Metadata-Version: 2.1
Name: paddle-nnUNet
Version: 0.0.2
Summary: nnUNet paddlepaddle version
Home-page: https://github.com/szuboy/paddle-nnUNet#readme
Author: szuboy
Author-email: szujeremy@gmail.com
License: Apache License
Project-URL: Documentation, https://paddle-nnunet.readthedocs.io/
Project-URL: Github, https://github.com/szuboy/paddle-nnUNet
Keywords: nnUNet paddle paddlepaddle python medical image segmentation
Platform: UNKNOWN
Requires-Python: >=3.0
Requires-Dist: numpy (>=1.9.2)
Requires-Dist: six (>=1.10.0)
Requires-Dist: SimpleITK (>=0.9.1)
